{"_type":"export","__export_format":4,"__export_date":"2022-05-04T02:53:08.906Z","__export_source":"insomnia.desktop.app:v2022.2.1","resources":[{"_id":"req_5d46148a20c5493a98e0e9542c3b1d7b","parentId":"fld_197d9a7cd66c4aab8fef4cee44152901","modified":1651611661765,"created":1651582626506,"url":"{{ _.base_url }}/respostas/del","name":"Delete","description":"","method":"DELETE","body":{"mimeType":"application/json","text":""},"parameters":[{"id":"pair_e31df57c209148df9402dc6e9fa57099","name":"pergunta","value":"2","description":""},{"id":"pair_585bb705c7964055bb4a49c97b5060c9","name":"resposta","value":"6","description":""}],"headers":[{"name":"Content-Type","value":"application/json","id":"pair_2bb1cd97cee149f1adfffc6a19564e46"}],"authentication":{},"metaSortKey":-1651582626506,"isPrivate":false,"settingStoreCookies":true,"settingSendCookies":true,"settingDisableRenderRequestBody":false,"settingEncodeUrl":true,"settingRebuildPath":true,"settingFollowRedirects":"global","_type":"request"},{"_id":"fld_197d9a7cd66c4aab8fef4cee44152901","parentId":"wrk_987711ad0a6c4a9a8a4322632191f5da","modified":1651582580109,"created":1651582580109,"name":"Respostas","description":"","environment":{},"environmentPropertyOrder":null,"metaSortKey":-1651582580109,"_type":"request_group"},{"_id":"wrk_987711ad0a6c4a9a8a4322632191f5da","parentId":null,"modified":1651582412864,"created":1651582412864,"name":"BeeDoo API","description":"","scope":"collection","_type":"workspace"},{"_id":"req_86419f73bd72485f922c60f6abee7212","parentId":"fld_197d9a7cd66c4aab8fef4cee44152901","modified":1651611632347,"created":1651582610996,"url":"{{ _.base_url }}/respostas/edit","name":"Update","description":"","method":"PUT","body":{"mimeType":"application/json","text":"{\n\t\"pergunta_id\": 4\n}"},"parameters":[{"id":"pair_a473cb51ffef4a62a6132d966dba341c","name":"pergunta","value":"2","description":""},{"id":"pair_4378a8499419426d8dc4446e9a299641","name":"resposta","value":"5","description":""}],"headers":[{"name":"Content-Type","value":"application/json","id":"pair_09b4e3b15d3b4e9ab624c3d54d8df9c6"}],"authentication":{},"metaSortKey":-1651582610996,"isPrivate":false,"settingStoreCookies":true,"settingSendCookies":true,"settingDisableRenderRequestBody":false,"settingEncodeUrl":true,"settingRebuildPath":true,"settingFollowRedirects":"global","_type":"request"},{"_id":"req_c57bcccd5bf94028bcfae9607ea6fd07","parentId":"fld_197d9a7cd66c4aab8fef4cee44152901","modified":1651611605129,"created":1651582605867,"url":"{{ _.base_url }}/respostas","name":"Index","description":"","method":"GET","body":{},"parameters":[{"id":"pair_d92618b096ef4586b3993264110f64fc","name":"pergunta","value":"2","description":"","disabled":false}],"headers":[],"authentication":{},"metaSortKey":-1651582605867,"isPrivate":false,"settingStoreCookies":true,"settingSendCookies":true,"settingDisableRenderRequestBody":false,"settingEncodeUrl":true,"settingRebuildPath":true,"settingFollowRedirects":"global","_type":"request"},{"_id":"req_e120ae84f17f440da0c900582ce53fea","parentId":"fld_197d9a7cd66c4aab8fef4cee44152901","modified":1651611536072,"created":1651582591276,"url":"{{ _.base_url }}/respostas/add/2","name":"Store","description":"","method":"POST","body":{"mimeType":"application/json","text":"{\n\t\"resposta\": \"45613\",\n\t\"resposta_valida\": false\n}"},"parameters":[],"headers":[{"name":"Content-Type","value":"application/json","id":"pair_0b9e02f5260e424daa57b006ed2d8a05"}],"authentication":{},"metaSortKey":-1651582591276,"isPrivate":false,"settingStoreCookies":true,"settingSendCookies":true,"settingDisableRenderRequestBody":false,"settingEncodeUrl":true,"settingRebuildPath":true,"settingFollowRedirects":"global","_type":"request"},{"_id":"req_f57b63b6957449dba5f3245d6fcf3ce1","parentId":"fld_257f1c0c9ea1430b9e33aa1d7d0a755d","modified":1651611687227,"created":1651582643618,"url":"{{ _.base_url }}/perguntas/del/5","name":"Delete","description":"","method":"DELETE","body":{"mimeType":"application/json","text":""},"parameters":[],"headers":[{"name":"Content-Type","value":"application/json","id":"pair_097518cdd02d478ea51f694319c63c90"}],"authentication":{},"metaSortKey":-1651582643618,"isPrivate":false,"settingStoreCookies":true,"settingSendCookies":true,"settingDisableRenderRequestBody":false,"settingEncodeUrl":true,"settingRebuildPath":true,"settingFollowRedirects":"global","_type":"request"},{"_id":"fld_257f1c0c9ea1430b9e33aa1d7d0a755d","parentId":"wrk_987711ad0a6c4a9a8a4322632191f5da","modified":1651582575782,"created":1651582575782,"name":"Perguntas","description":"","environment":{},"environmentPropertyOrder":null,"metaSortKey":-1651582575782,"_type":"request_group"},{"_id":"req_97b95b1b022c4b7c8825519e4bed32f0","parentId":"fld_257f1c0c9ea1430b9e33aa1d7d0a755d","modified":1651612152447,"created":1651582639378,"url":"{{ _.base_url }}/perguntas/edit/1","name":"Update","description":"","method":"PUT","body":{"mimeType":"application/json","text":"{\n\t\"pergunta\": \"Pergunta Editada\"\n}"},"parameters":[],"headers":[{"name":"Content-Type","value":"application/json","id":"pair_62b23693dfae4571bf7b7511ce7f9155"}],"authentication":{},"metaSortKey":-1651582639378,"isPrivate":false,"settingStoreCookies":true,"settingSendCookies":true,"settingDisableRenderRequestBody":false,"settingEncodeUrl":true,"settingRebuildPath":true,"settingFollowRedirects":"global","_type":"request"},{"_id":"req_f5a6e52c43cc45c69f2aadd8258c8227","parentId":"fld_257f1c0c9ea1430b9e33aa1d7d0a755d","modified":1651582691283,"created":1651582634979,"url":"{{ _.base_url }}/perguntas","name":"Index","description":"","method":"GET","body":{},"parameters":[],"headers":[],"authentication":{},"metaSortKey":-1651582634979,"isPrivate":false,"settingStoreCookies":true,"settingSendCookies":true,"settingDisableRenderRequestBody":false,"settingEncodeUrl":true,"settingRebuildPath":true,"settingFollowRedirects":"global","_type":"request"},{"_id":"req_ba1d1ae3892341059af78ba2cb3e15e4","parentId":"fld_257f1c0c9ea1430b9e33aa1d7d0a755d","modified":1651610998415,"created":1651582631379,"url":"{{ _.base_url }}/perguntas/add","name":"Store","description":"","method":"POST","body":{"mimeType":"application/json","text":"{\n\t\"pergunta\": \"Tenho 2 letras um buraco no meio e o pessoal gosta de me dar de presente\"\n}"},"parameters":[],"headers":[{"name":"Content-Type","value":"application/json","id":"pair_f4193bc07e134351b8f7ce84d666b9a2"}],"authentication":{},"metaSortKey":-1651582631379,"isPrivate":false,"settingStoreCookies":true,"settingSendCookies":true,"settingDisableRenderRequestBody":false,"settingEncodeUrl":true,"settingRebuildPath":true,"settingFollowRedirects":"global","_type":"request"},{"_id":"env_3fdc565aea7e598e1ecf928c712053e1ee2cdb6a","parentId":"wrk_987711ad0a6c4a9a8a4322632191f5da","modified":1651582959999,"created":1651582412875,"name":"Base Environment","data":{"base_url":"http://localhost:3333"},"dataPropertyOrder":{"&":["base_url"]},"color":null,"isPrivate":false,"metaSortKey":1651582412876,"_type":"environment"},{"_id":"jar_3fdc565aea7e598e1ecf928c712053e1ee2cdb6a","parentId":"wrk_987711ad0a6c4a9a8a4322632191f5da","modified":1651582412881,"created":1651582412881,"name":"Default Jar","cookies":[],"_type":"cookie_jar"},{"_id":"spc_2e6bee77cd594a689d9ec2e7226b1b55","parentId":"wrk_987711ad0a6c4a9a8a4322632191f5da","modified":1651582412866,"created":1651582412866,"fileName":"BeeDoo API","contents":"","contentType":"yaml","_type":"api_spec"}]}